django_contracts/__init__.py
django_contracts/apps.py
django_contracts/classes.py
django_contracts/contracts.py
django_contracts/errors.py
django_contracts/normalizers.py
django_contracts/request.py
django_contracts/response.py
django_contracts/urls.py
django_contracts/utils.py
django_contracts/__pycache__/__init__.cpython-37.pyc
django_contracts/__pycache__/__init__.cpython-38.pyc
django_contracts/__pycache__/contracts.cpython-37.pyc
django_contracts/__pycache__/contracts.cpython-38.pyc
django_contracts/__pycache__/discovery.cpython-37.pyc
django_contracts/__pycache__/errors.cpython-37.pyc
django_contracts/__pycache__/errors.cpython-38.pyc
django_contracts/__pycache__/normalizers.cpython-37.pyc
django_contracts/__pycache__/normalizers.cpython-38.pyc
django_contracts/__pycache__/request.cpython-37.pyc
django_contracts/__pycache__/response.cpython-37.pyc
django_contracts/__pycache__/urls.cpython-37.pyc
django_contracts/__pycache__/utils.cpython-37.pyc
django_contracts/discovery/__init__.py
django_contracts/discovery/primitives.py
django_contracts/discovery/views.py
django_contracts/discovery/__pycache__/__init__.cpython-37.pyc
django_contracts/discovery/__pycache__/__init__.cpython-38.pyc
django_contracts/discovery/__pycache__/primitives.cpython-37.pyc
django_contracts/discovery/__pycache__/primitives.cpython-38.pyc
django_contracts/discovery/__pycache__/views.cpython-37.pyc
django_contracts/tests/__init__.py
django_contracts/tests/settings.py
django_contracts/tests/test_contracts.py
django_contracts/tests/test_discovery.py
django_contracts/tests/test_error_mapping.py
django_contracts/tests/test_user_forms.py
django_contracts/tests/__pycache__/__init__.cpython-37.pyc
django_contracts/tests/__pycache__/settings.cpython-37.pyc
django_contracts/tests/__pycache__/test_contracts.cpython-37-pytest-5.3.5.pyc
django_contracts/tests/__pycache__/test_discovery.cpython-37-pytest-5.3.5.pyc
django_contracts/tests/__pycache__/test_error_mapping.cpython-37-pytest-5.3.5.pyc
django_contracts-0.4.5.dist-info/METADATA
django_contracts-0.4.5.dist-info/WHEEL
django_contracts-0.4.5.dist-info/top_level.txt
django_contracts-0.4.5.dist-info/RECORD
