Metadata-Version: 2.1
Name: django-contracts
Version: 0.4.5
Summary: A lightweight API validation library built on top of Django forms.
Home-page: https://github.com/MrSage/django_api_contracts
Author: Collin Sage
Author-email: clln.sage@yahoo.com
License: MIT
Platform: UNKNOWN
Classifier: License :: OSI Approved :: MIT License
Classifier: Programming Language :: Python
Classifier: Programming Language :: Python :: 3
Classifier: Programming Language :: Python :: 3.6
Classifier: Programming Language :: Python :: Implementation :: CPython
Classifier: Programming Language :: Python :: Implementation :: PyPy
Requires-Python: >=3.8.0
Requires-Dist: django
